scikit_learn_pipeline_utils-0.0.7.data/data/LICENSE
sklearn_pipeline_utils/__init__.py
sklearn_pipeline_utils/dataframetransformers.py
scikit_learn_pipeline_utils-0.0.7.dist-info/LICENSE
scikit_learn_pipeline_utils-0.0.7.dist-info/METADATA
scikit_learn_pipeline_utils-0.0.7.dist-info/WHEEL
scikit_learn_pipeline_utils-0.0.7.dist-info/top_level.txt
scikit_learn_pipeline_utils-0.0.7.dist-info/RECORD
