Metadata-Version: 2.1
Name: scikit-learn-pipeline-utils
Version: 0.0.7
Summary: Custom Pipeline Transformers for Sklearn Pipelines
Home-page: https://github.com/deltahedge1/scikit-learn-pipeline-utils
Author: Ish Hassan
Author-email: ishassan90@gmail.com
License: MIT
Platform: UNKNOWN
Classifier: License :: OSI Approved :: MIT License
Classifier: Programming Language :: Python :: 3
Classifier: Programming Language :: Python :: 3.7
Requires-Dist: scikit-learn
Requires-Dist: pandas
